whorl/__init__.py
whorl/agents.py
whorl/cli.py
whorl/models.py
whorl/server.py
whorl/frontend/dist/bookmarklet.html
whorl/frontend/dist/icon-192.png
whorl/frontend/dist/icon-512.png
whorl/frontend/dist/icon.svg
whorl/frontend/dist/index.html
whorl/frontend/dist/manifest.json
whorl/frontend/dist/sw.js
whorl/frontend/dist/vite.svg
whorl/frontend/dist/assets/index-C-dIhJIY.css
whorl/frontend/dist/assets/index-DDYqo8_f.js
whorl/lib/__init__.py
whorl/lib/text_edit.py
whorl/lib/utils.py
whorled-0.1.1.dist-info/METADATA
whorled-0.1.1.dist-info/WHEEL
whorled-0.1.1.dist-info/entry_points.txt
whorled-0.1.1.dist-info/top_level.txt
whorled-0.1.1.dist-info/RECORD
