Metadata-Version: 2.4
Name: whorled
Version: 0.1.1
Summary: Personal knowledge ingestion server
Requires-Python: >=3.12
Requires-Dist: anthropic>=0.40.0
Requires-Dist: fastapi>=0.127.0
Requires-Dist: fastmcp>=2.14.1
Requires-Dist: httpx>=0.28.1
Requires-Dist: python-dotenv>=1.2.1
Requires-Dist: pyyaml>=6.0.3
Requires-Dist: uvicorn>=0.40.0
